{"all_plays":[{"result_event":"Penalty","result_event_code":"COL10367","result_event_type_id":"PENALTY","result_description":"Paul Stastny Hooking against Mason Raymond","result_secondary_type":"Hooking","result_penalty_minutes":2,"about_event_idx":3,"about_event_id":10367,"about_period":1,"about_period_type":"REGULAR","about_ordinal_num":"1st","about_period_time":"06:07","about_period_time_remaining":"","about_date_time":"2009-10-03T19:00:00Z","about_goals_away":0,"about_goals_home":0,"team_id":21,"team_name":"Colorado Avalanche","team_link":"/api/v1/teams/21","team_tri_code":"COL","player_type_1":"PenaltyOn","player_id_1":8471669,"player_full_name_1":"Paul Stastny","player_link_1":"/api/v1/people/8471669","player_type_2":"DrewBy","player_id_2":8471664,"player_full_name_2":"Mason Raymond","player_link_2":"/api/v1/people/8471664"},{"result_event":"Goal","result_event_code":"COL892","result_event_type_id":"GOAL","result_description":"Wojtek Wolski (3) Wrist Shot, assists: Paul Stastny (3), Milan Hejduk (2)","result_game_winning_goal":true,"result_empty_net":false,"result_strength_code":"EVEN","result_strength_name":"Even","about_event_idx":0,"about_event_id":892,"about_period":1,"about_period_type":"REGULAR","about_ordinal_num":"1st","about_period_time":"14:52","about_period_time_remaining":"","about_date_time":"2009-10-03T19:00:00Z","about_goals_away":0,"about_goals_home":1,"team_id":21,"team_name":"Colorado Avalanche","team_link":"/api/v1/teams/21","team_tri_code":"COL","player_type_1":"Scorer","player_id_1":8471234,"player_full_name_1":"Wojtek Wolski","player_link_1":"/api/v1/people/8471234","player_type_2":"Assist","player_id_2":8471669,"player_full_name_2":"Paul Stastny","player_link_2":"/api/v1/people/8471669"},{"result_event":"Penalty","result_event_code":"COL10969","result_event_type_id":"PENALTY","result_description":"Darcy Tucker Roughing against Kevin Bieksa","result_secondary_type":"Roughing","result_penalty_minutes":2,"about_event_idx":4,"about_event_id":10969,"about_period":1,"about_period_type":"REGULAR","about_ordinal_num":"1st","about_period_time":"16:09","about_period_time_remaining":"","about_date_time":"2009-10-03T19:00:00Z","about_goals_away":0,"about_goals_home":1,"team_id":21,"team_name":"Colorado Avalanche","team_link":"/api/v1/teams/21","team_tri_code":"COL","player_type_1":"PenaltyOn","player_id_1":8459574,"player_full_name_1":"Darcy Tucker","player_link_1":"/api/v1/people/8459574","player_type_2":"DrewBy","player_id_2":8469598,"player_full_name_2":"Kevin Bieksa","player_link_2":"/api/v1/people/8469598"},{"result_event":"Penalty","result_event_code":"COL20969","result_event_type_id":"PENALTY","result_description":"Kevin Bieksa Roughing against Darcy Tucker","result_secondary_type":"Roughing","result_penalty_minutes":2,"about_event_idx":5,"about_event_id":20969,"about_period":1,"about_period_type":"REGULAR","about_ordinal_num":"1st","about_period_time":"16:09","about_period_time_remaining":"","about_date_time":"2009-10-03T19:00:00Z","about_goals_away":0,"about_goals_home":1,"team_id":23,"team_name":"Vancouver Canucks","team_link":"/api/v1/teams/23","team_tri_code":"VAN","player_type_1":"PenaltyOn","player_id_1":8469598,"player_full_name_1":"Kevin Bieksa","player_link_1":"/api/v1/people/8469598","player_type_2":"DrewBy","player_id_2":8459574,"player_full_name_2":"Darcy Tucker","player_link_2":"/api/v1/people/8459574"},{"result_event":"Penalty","result_event_code":"COL11506","result_event_type_id":"PENALTY","result_description":"Kyle Quincey Interference against Alexandre Burrows","result_secondary_type":"Interference","result_penalty_minutes":2,"about_event_idx":6,"about_event_id":11506,"about_period":2,"about_period_type":"REGULAR","about_ordinal_num":"2nd","about_period_time":"05:06","about_period_time_remaining":"","about_date_time":"2009-10-03T19:00:00Z","about_goals_away":0,"about_goals_home":1,"team_id":21,"team_name":"Colorado Avalanche","team_link":"/api/v1/teams/21","team_tri_code":"COL","player_type_1":"PenaltyOn","player_id_1":8470724,"player_full_name_1":"Kyle Quincey","player_link_1":"/api/v1/people/8470724","player_type_2":"DrewBy","player_id_2":8470358,"player_full_name_2":"Alexandre Burrows","player_link_2":"/api/v1/people/8470358"},{"result_event":"Penalty","result_event_code":"COL11784","result_event_type_id":"PENALTY","result_description":"Alexander Edler Hooking against Matt Duchene","result_secondary_type":"Hooking","result_penalty_minutes":2,"about_event_idx":7,"about_event_id":11784,"about_period":2,"about_period_type":"REGULAR","about_ordinal_num":"2nd","about_period_time":"09:44","about_period_time_remaining":"","about_date_time":"2009-10-03T19:00:00Z","about_goals_away":0,"about_goals_home":1,"team_id":23,"team_name":"Vancouver Canucks","team_link":"/api/v1/teams/23","team_tri_code":"VAN","player_type_1":"PenaltyOn","player_id_1":8471303,"player_full_name_1":"Alexander Edler","player_link_1":"/api/v1/people/8471303","player_type_2":"DrewBy","player_id_2":8475168,"player_full_name_2":"Matt Duchene","player_link_2":"/api/v1/people/8475168"},{"result_event":"Penalty","result_event_code":"COL11942","result_event_type_id":"PENALTY","result_description":"Alexandre Burrows Interference against Kyle Quincey","result_secondary_type":"Interference","result_penalty_minutes":2,"about_event_idx":8,"about_event_id":11942,"about_period":2,"about_period_type":"REGULAR","about_ordinal_num":"2nd","about_period_time":"12:22","about_period_time_remaining":"","about_date_time":"2009-10-03T19:00:00Z","about_goals_away":0,"about_goals_home":1,"team_id":23,"team_name":"Vancouver Canucks","team_link":"/api/v1/teams/23","team_tri_code":"VAN","player_type_1":"PenaltyOn","player_id_1":8470358,"player_full_name_1":"Alexandre Burrows","player_link_1":"/api/v1/people/8470358","player_type_2":"DrewBy","player_id_2":8470724,"player_full_name_2":"Kyle Quincey","player_link_2":"/api/v1/people/8470724"},{"result_event":"Penalty","result_event_code":"COL12110","result_event_type_id":"PENALTY","result_description":"Henrik Sedin Holding against Ryan O'Reilly","result_secondary_type":"Holding","result_penalty_minutes":2,"about_event_idx":9,"about_event_id":12110,"about_period":2,"about_period_type":"REGULAR","about_ordinal_num":"2nd","about_period_time":"15:10","about_period_time_remaining":"","about_date_time":"2009-10-03T19:00:00Z","about_goals_away":0,"about_goals_home":1,"team_id":23,"team_name":"Vancouver Canucks","team_link":"/api/v1/teams/23","team_tri_code":"VAN","player_type_1":"PenaltyOn","player_id_1":8467876,"player_full_name_1":"Henrik Sedin","player_link_1":"/api/v1/people/8467876","player_type_2":"DrewBy","player_id_2":8475158,"player_full_name_2":"Ryan O'Reilly","player_link_2":"/api/v1/people/8475158"},{"result_event":"Goal","result_event_code":"COL2116","result_event_type_id":"GOAL","result_description":"Paul Stastny (1) Tip-In, assists: Milan Hejduk (3), Kyle Quincey (2)","result_game_winning_goal":false,"result_empty_net":false,"result_strength_code":"PPG","result_strength_name":"Power Play","about_event_idx":1,"about_event_id":2116,"about_period":2,"about_period_type":"REGULAR","about_ordinal_num":"2nd","about_period_time":"15:16","about_period_time_remaining":"","about_date_time":"2009-10-03T19:00:00Z","about_goals_away":0,"about_goals_home":2,"team_id":21,"team_name":"Colorado Avalanche","team_link":"/api/v1/teams/21","team_tri_code":"COL","player_type_1":"Scorer","player_id_1":8471669,"player_full_name_1":"Paul Stastny","player_link_1":"/api/v1/people/8471669","player_type_2":"Assist","player_id_2":8460577,"player_full_name_2":"Milan Hejduk","player_link_2":"/api/v1/people/8460577"},{"result_event":"Penalty","result_event_code":"COL12179","result_event_type_id":"PENALTY","result_description":"Adam Foote Tripping against Sergei Shirokov","result_secondary_type":"Tripping","result_penalty_minutes":2,"about_event_idx":10,"about_event_id":12179,"about_period":2,"about_period_type":"REGULAR","about_ordinal_num":"2nd","about_period_time":"16:19","about_period_time_remaining":"","about_date_time":"2009-10-03T19:00:00Z","about_goals_away":0,"about_goals_home":2,"team_id":21,"team_name":"Colorado Avalanche","team_link":"/api/v1/teams/21","team_tri_code":"COL","player_type_1":"PenaltyOn","player_id_1":8456283,"player_full_name_1":"Adam Foote","player_link_1":"/api/v1/people/8456283","player_type_2":"DrewBy","player_id_2":8473488,"player_full_name_2":"Sergei Shirokov","player_link_2":"/api/v1/people/8473488"},{"result_event":"Penalty","result_event_code":"COL12395","result_event_type_id":"PENALTY","result_description":"Daniel Sedin Holding against Milan Hejduk","result_secondary_type":"Holding","result_penalty_minutes":2,"about_event_idx":11,"about_event_id":12395,"about_period":2,"about_period_type":"REGULAR","about_ordinal_num":"2nd","about_period_time":"19:55","about_period_time_remaining":"","about_date_time":"2009-10-03T19:00:00Z","about_goals_away":0,"about_goals_home":2,"team_id":23,"team_name":"Vancouver Canucks","team_link":"/api/v1/teams/23","team_tri_code":"VAN","player_type_1":"PenaltyOn","player_id_1":8467875,"player_full_name_1":"Daniel Sedin","player_link_1":"/api/v1/people/8467875","player_type_2":"DrewBy","player_id_2":8460577,"player_full_name_2":"Milan Hejduk","player_link_2":"/api/v1/people/8460577"},{"result_event":"Penalty","result_event_code":"COL12639","result_event_type_id":"PENALTY","result_description":"Ryan Kesler Holding against Milan Hejduk","result_secondary_type":"Holding","result_penalty_minutes":2,"about_event_idx":12,"about_event_id":12639,"about_period":3,"about_period_type":"REGULAR","about_ordinal_num":"3rd","about_period_time":"03:59","about_period_time_remaining":"","about_date_time":"2009-10-03T19:00:00Z","about_goals_away":0,"about_goals_home":2,"team_id":23,"team_name":"Vancouver Canucks","team_link":"/api/v1/teams/23","team_tri_code":"VAN","player_type_1":"PenaltyOn","player_id_1":8470616,"player_full_name_1":"Ryan Kesler","player_link_1":"/api/v1/people/8470616","player_type_2":"DrewBy","player_id_2":8460577,"player_full_name_2":"Milan Hejduk","player_link_2":"/api/v1/people/8460577"},{"result_event":"Goal","result_event_code":"COL2723","result_event_type_id":"GOAL","result_description":"Darcy Tucker (2) Wrist Shot, assists: Wojtek Wolski (1), Brett Clark (2)","result_game_winning_goal":false,"result_empty_net":false,"result_strength_code":"PPG","result_strength_name":"Power Play","about_event_idx":2,"about_event_id":2723,"about_period":3,"about_period_type":"REGULAR","about_ordinal_num":"3rd","about_period_time":"05:23","about_period_time_remaining":"","about_date_time":"2009-10-03T19:00:00Z","about_goals_away":0,"about_goals_home":3,"team_id":21,"team_name":"Colorado Avalanche","team_link":"/api/v1/teams/21","team_tri_code":"COL","player_type_1":"Scorer","player_id_1":8459574,"player_full_name_1":"Darcy Tucker","player_link_1":"/api/v1/people/8459574","player_type_2":"Assist","player_id_2":8471234,"player_full_name_2":"Wojtek Wolski","player_link_2":"/api/v1/people/8471234"},{"result_event":"Penalty","result_event_code":"COL13127","result_event_type_id":"PENALTY","result_description":"Shane O'Brien Elbowing against Matt Hendricks","result_secondary_type":"Elbowing","result_penalty_minutes":2,"about_event_idx":13,"about_event_id":13127,"about_period":3,"about_period_type":"REGULAR","about_ordinal_num":"3rd","about_period_time":"12:07","about_period_time_remaining":"","about_date_time":"2009-10-03T19:00:00Z","about_goals_away":0,"about_goals_home":3,"team_id":23,"team_name":"Vancouver Canucks","team_link":"/api/v1/teams/23","team_tri_code":"VAN","player_type_1":"PenaltyOn","player_id_1":8470839,"player_full_name_1":"Shane O'Brien","player_link_1":"/api/v1/people/8470839","player_type_2":"DrewBy","player_id_2":8468611,"player_full_name_2":"Matt Hendricks","player_link_2":"/api/v1/people/8468611"},{"result_event":"Penalty","result_event_code":"COL13587","result_event_type_id":"PENALTY","result_description":"Cody McLeod Fighting against Willie Mitchell","result_secondary_type":"Fighting","result_penalty_minutes":5,"about_event_idx":14,"about_event_id":13587,"about_period":3,"about_period_type":"REGULAR","about_ordinal_num":"3rd","about_period_time":"19:47","about_period_time_remaining":"","about_date_time":"2009-10-03T19:00:00Z","about_goals_away":0,"about_goals_home":3,"team_id":21,"team_name":"Colorado Avalanche","team_link":"/api/v1/teams/21","team_tri_code":"COL","player_type_1":"PenaltyOn","player_id_1":8471657,"player_full_name_1":"Cody McLeod","player_link_1":"/api/v1/people/8471657","player_type_2":"DrewBy","player_id_2":8465185,"player_full_name_2":"Willie Mitchell","player_link_2":"/api/v1/people/8465185"},{"result_event":"Penalty","result_event_code":"COL23587","result_event_type_id":"PENALTY","result_description":"Willie Mitchell Fighting against Cody McLeod","result_secondary_type":"Fighting","result_penalty_minutes":5,"about_event_idx":15,"about_event_id":23587,"about_period":3,"about_period_type":"REGULAR","about_ordinal_num":"3rd","about_period_time":"19:47","about_period_time_remaining":"","about_date_time":"2009-10-03T19:00:00Z","about_goals_away":0,"about_goals_home":3,"team_id":23,"team_name":"Vancouver Canucks","team_link":"/api/v1/teams/23","team_tri_code":"VAN","player_type_1":"PenaltyOn","player_id_1":8465185,"player_full_name_1":"Willie Mitchell","player_link_1":"/api/v1/people/8465185","player_type_2":"DrewBy","player_id_2":8471657,"player_full_name_2":"Cody McLeod","player_link_2":"/api/v1/people/8471657"},{"result_event":"Penalty","result_event_code":"COL13600","result_event_type_id":"PENALTY","result_description":"Darcy Tucker Fighting against Kevin Bieksa","result_secondary_type":"Fighting","result_penalty_minutes":5,"about_event_idx":16,"about_event_id":13600,"about_period":3,"about_period_type":"REGULAR","about_ordinal_num":"3rd","about_period_time":"20:00","about_period_time_remaining":"","about_date_time":"2009-10-03T19:00:00Z","about_goals_away":0,"about_goals_home":3,"team_id":21,"team_name":"Colorado Avalanche","team_link":"/api/v1/teams/21","team_tri_code":"COL","player_type_1":"PenaltyOn","player_id_1":8459574,"player_full_name_1":"Darcy Tucker","player_link_1":"/api/v1/people/8459574","player_type_2":"DrewBy","player_id_2":8469598,"player_full_name_2":"Kevin Bieksa","player_link_2":"/api/v1/people/8469598"},{"result_event":"Penalty","result_event_code":"COL23600","result_event_type_id":"PENALTY","result_description":"Kevin Bieksa Fighting against Darcy Tucker","result_secondary_type":"Fighting","result_penalty_minutes":5,"about_event_idx":17,"about_event_id":23600,"about_period":3,"about_period_type":"REGULAR","about_ordinal_num":"3rd","about_period_time":"20:00","about_period_time_remaining":"","about_date_time":"2009-10-03T19:00:00Z","about_goals_away":0,"about_goals_home":3,"team_id":23,"team_name":"Vancouver Canucks","team_link":"/api/v1/teams/23","team_tri_code":"VAN","player_type_1":"PenaltyOn","player_id_1":8469598,"player_full_name_1":"Kevin Bieksa","player_link_1":"/api/v1/people/8469598","player_type_2":"DrewBy","player_id_2":8459574,"player_full_name_2":"Darcy Tucker","player_link_2":"/api/v1/people/8459574"}],"scoring_plays":[1,8,12],"penalty_plays":[0,2,3,4,5,6,7,9,10,11,13,14,15,16,17],"plays_by_period":[{"startIndex":0,"plays":[0,1,2,3],"endIndex":2},{"startIndex":4,"plays":[4,5,6,7,8,9,10],"endIndex":9},{"startIndex":11,"plays":[11,12,13,14,15,16,17],"endIndex":17}],"current_play":{"players":[{"player":{"id":8469598,"fullName":"Kevin Bieksa","link":"/api/v1/people/8469598"},"playerType":"PenaltyOn"},{"player":{"id":8459574,"fullName":"Darcy Tucker","link":"/api/v1/people/8459574"},"playerType":"DrewBy"}],"result":{"event":["Penalty"],"eventCode":["COL23600"],"eventTypeId":["PENALTY"],"description":["Kevin Bieksa Fighting against Darcy Tucker"],"secondaryType":["Fighting"],"penaltyMinutes":[5]},"about":{"eventIdx":[17],"eventId":[23600],"period":[3],"periodType":["REGULAR"],"ordinalNum":["3rd"],"periodTime":["20:00"],"periodTimeRemaining":[""],"dateTime":["2009-10-03T19:00:00Z"],"goals":{"away":[0],"home":[3]}},"coordinates":{},"team":{"id":[23],"name":["Vancouver Canucks"],"link":["/api/v1/teams/23"],"triCode":["VAN"]}},"linescore":{"currentPeriod":[3],"currentPeriodOrdinal":["3rd"],"currentPeriodTimeRemaining":["Final"],"periods":[{"periodType":"REGULAR","num":1,"ordinalNum":"1st","home":{"goals":1,"shotsOnGoal":10,"rinkSide":"right"},"away":{"goals":0,"shotsOnGoal":12,"rinkSide":"left"}},{"periodType":"REGULAR","num":2,"ordinalNum":"2nd","home":{"goals":1,"shotsOnGoal":7,"rinkSide":"left"},"away":{"goals":0,"shotsOnGoal":12,"rinkSide":"right"}},{"periodType":"REGULAR","num":3,"ordinalNum":"3rd","home":{"goals":1,"shotsOnGoal":10,"rinkSide":"right"},"away":{"goals":0,"shotsOnGoal":11,"rinkSide":"left"}}],"shootoutInfo":{"away":{"scores":[0],"attempts":[0]},"home":{"scores":[0],"attempts":[0]}},"teams":{"home":{"team":{"id":[21],"name":["Colorado Avalanche"],"link":["/api/v1/teams/21"],"abbreviation":["COL"],"triCode":["COL"]},"goals":[3],"shotsOnGoal":[27],"goaliePulled":[false],"numSkaters":[0],"powerPlay":[false]},"away":{"team":{"id":[23],"name":["Vancouver Canucks"],"link":["/api/v1/teams/23"],"abbreviation":["VAN"],"triCode":["VAN"]},"goals":[0],"shotsOnGoal":[35],"goaliePulled":[false],"numSkaters":[0],"powerPlay":[false]}},"powerPlayStrength":["Even"],"hasShootout":[false],"intermissionInfo":{"intermissionTimeRemaining":[0],"intermissionTimeElapsed":[0],"inIntermission":[false]}},"decisions":{"winner":{"id":[8467950],"fullName":["Craig Anderson"],"link":["/api/v1/people/8467950"]},"loser":{"id":[8466141],"fullName":["Roberto Luongo"],"link":["/api/v1/people/8466141"]},"firstStar":{"id":[8467950],"fullName":["Craig Anderson"],"link":["/api/v1/people/8467950"]},"secondStar":{"id":[8471669],"fullName":["Paul Stastny"],"link":["/api/v1/people/8471669"]},"thirdStar":{"id":[8475168],"fullName":["Matt Duchene"],"link":["/api/v1/people/8475168"]}},"team_box":[{"team_id":23,"team_name":"Vancouver Canucks","link":"/api/v1/teams/23","abbreviation":"VAN","triCode":"VAN","goals":0,"pim":24,"shots":35,"powerPlayPercentage":"0.0","powerPlayGoals":0,"powerPlayOpportunities":3,"blocked":12,"takeaways":11,"giveaways":7,"hits":17},{"team_id":21,"team_name":"Colorado Avalanche","link":"/api/v1/teams/21","abbreviation":"COL","triCode":"COL","goals":3,"pim":18,"shots":27,"powerPlayPercentage":"33.3","powerPlayGoals":2,"powerPlayOpportunities":6,"blocked":16,"takeaways":13,"giveaways":9,"hits":19}],"players_box":[{"id":8465202,"full_name":"Sami Salo","link":"/api/v1/people/8465202","shoots_catches":"R","roster_status":"Y","jersey_number":"6","code":"D","name":"Defenseman","type":"Defenseman","abbreviation":"D","skater_stats_time_on_ice":"21:33","skater_stats_assists":0,"skater_stats_goals":0,"skater_stats_shots":2,"skater_stats_power_play_goals":0,"skater_stats_power_play_assists":0,"skater_stats_penalty_minutes":0,"skater_stats_face_off_wins":0,"skater_stats_faceoff_taken":0,"skater_stats_short_handed_goals":0,"skater_stats_short_handed_assists":0,"skater_stats_plus_minus":-1,"skater_stats_even_time_on_ice":"14:10","skater_stats_power_play_time_on_ice":"2:51","skater_stats_short_handed_time_on_ice":"4:32","home_away":"Away"},{"id":8467876,"full_name":"Henrik Sedin","link":"/api/v1/people/8467876","shoots_catches":"L","roster_status":"Y","jersey_number":"33","code":"C","name":"Center","type":"Forward","abbreviation":"C","skater_stats_time_on_ice":"18:39","skater_stats_assists":0,"skater_stats_goals":0,"skater_stats_shots":1,"skater_stats_power_play_goals":0,"skater_stats_power_play_assists":0,"skater_stats_penalty_minutes":2,"skater_stats_face_off_wins":12,"skater_stats_faceoff_taken":19,"skater_stats_short_handed_goals":0,"skater_stats_short_handed_assists":0,"skater_stats_plus_minus":0,"skater_stats_even_time_on_ice":"14:28","skater_stats_power_play_time_on_ice":"3:07","skater_stats_short_handed_time_on_ice":"1:04","skater_stats_face_off_pct":63.16,"home_away":"Away"},{"id":8470616,"full_name":"Ryan Kesler","link":"/api/v1/people/8470616","shoots_catches":"R","roster_status":"Y","jersey_number":"17","code":"C","name":"Center","type":"Forward","abbreviation":"C","skater_stats_time_on_ice":"18:02","skater_stats_assists":0,"skater_stats_goals":0,"skater_stats_shots":0,"skater_stats_power_play_goals":0,"skater_stats_power_play_assists":0,"skater_stats_penalty_minutes":2,"skater_stats_face_off_wins":10,"skater_stats_faceoff_taken":17,"skater_stats_short_handed_goals":0,"skater_stats_short_handed_assists":0,"skater_stats_plus_minus":0,"skater_stats_even_time_on_ice":"12:23","skater_stats_power_play_time_on_ice":"2:38","skater_stats_short_handed_time_on_ice":"3:01","skater_stats_face_off_pct":58.82,"home_away":"Away"},{"id":8467875,"full_name":"Daniel Sedin","link":"/api/v1/people/8467875","shoots_catches":"L","roster_status":"Y","jersey_number":"22","code":"L","name":"Left Wing","type":"Forward","abbreviation":"LW","skater_stats_time_on_ice":"16:54","skater_stats_assists":0,"skater_stats_goals":0,"skater_stats_shots":9,"skater_stats_power_play_goals":0,"skater_stats_power_play_assists":0,"skater_stats_penalty_minutes":2,"skater_stats_face_off_wins":0,"skater_stats_faceoff_taken":0,"skater_stats_short_handed_goals":0,"skater_stats_short_handed_assists":0,"skater_stats_plus_minus":-1,"skater_stats_even_time_on_ice":"13:32","skater_stats_power_play_time_on_ice":"3:07","skater_stats_short_handed_time_on_ice":"0:15","home_away":"Away"},{"id":8471628,"full_name":"Rick Rypien","link":"/api/v1/people/8471628","shoots_catches":"R","roster_status":"N","jersey_number":"37","code":"C","name":"Center","type":"Forward","abbreviation":"C","skater_stats_time_on_ice":"9:30","skater_stats_assists":0,"skater_stats_goals":0,"skater_stats_shots":1,"skater_stats_power_play_goals":0,"skater_stats_power_play_assists":0,"skater_stats_penalty_minutes":0,"skater_stats_face_off_wins":0,"skater_stats_faceoff_taken":1,"skater_stats_short_handed_goals":0,"skater_stats_short_handed_assists":0,"skater_stats_plus_minus":0,"skater_stats_even_time_on_ice":"6:28","skater_stats_power_play_time_on_ice":"0:00","skater_stats_short_handed_time_on_ice":"3:02","skater_stats_face_off_pct":0,"home_away":"Away"},{"id":8470839,"full_name":"Shane O'Brien","link":"/api/v1/people/8470839","shoots_catches":"L","roster_status":"N","jersey_number":"55","code":"D","name":"Defenseman","type":"Defenseman","abbreviation":"D","skater_stats_time_on_ice":"18:21","skater_stats_assists":0,"skater_stats_goals":0,"skater_stats_shots":1,"skater_stats_power_play_goals":0,"skater_stats_power_play_assists":0,"skater_stats_penalty_minutes":2,"skater_stats_face_off_wins":0,"skater_stats_faceoff_taken":0,"skater_stats_short_handed_goals":0,"skater_stats_short_handed_assists":0,"skater_stats_plus_minus":0,"skater_stats_even_time_on_ice":"15:20","skater_stats_power_play_time_on_ice":"0:00","skater_stats_short_handed_time_on_ice":"3:01","home_away":"Away"},{"id":8470609,"full_name":"Steve Bernier","link":"/api/v1/people/8470609","shoots_catches":"R","roster_status":"Y","jersey_number":"18","code":"R","name":"Right Wing","type":"Forward","abbreviation":"RW","skater_stats_time_on_ice":"13:21","skater_stats_assists":0,"skater_stats_goals":0,"skater_stats_shots":1,"skater_stats_power_play_goals":0,"skater_stats_power_play_assists":0,"skater_stats_penalty_minutes":0,"skater_stats_face_off_wins":0,"skater_stats_faceoff_taken":0,"skater_stats_short_handed_goals":0,"skater_stats_short_handed_assists":0,"skater_stats_plus_minus":0,"skater_stats_even_time_on_ice":"9:42","skater_stats_power_play_time_on_ice":"1:54","skater_stats_short_handed_time_on_ice":"1:45","home_away":"Away"},{"id":8465185,"full_name":"Willie Mitchell","link":"/api/v1/people/8465185","shoots_catches":"L","roster_status":"I","jersey_number":"8","code":"D","name":"Defenseman","type":"Defenseman","abbreviation":"D","skater_stats_time_on_ice":"22:50","skater_stats_assists":0,"skater_stats_goals":0,"skater_stats_shots":0,"skater_stats_power_play_goals":0,"skater_stats_power_play_assists":0,"skater_stats_penalty_minutes":5,"skater_stats_face_off_wins":0,"skater_stats_faceoff_taken":0,"skater_stats_short_handed_goals":0,"skater_stats_short_handed_assists":0,"skater_stats_plus_minus":-1,"skater_stats_even_time_on_ice":"17:01","skater_stats_power_play_time_on_ice":"0:05","skater_stats_short_handed_time_on_ice":"5:44","home_away":"Away"},{"id":8467463,"full_name":"Mikael Samuelsson","link":"/api/v1/people/8467463","shoots_catches":"R","roster_status":"I","jersey_number":"26","code":"R","name":"Right Wing","type":"Forward","abbreviation":"RW","skater_stats_time_on_ice":"15:18","skater_stats_assists":0,"skater_stats_goals":0,"skater_stats_shots":1,"skater_stats_power_play_goals":0,"skater_stats_power_play_assists":0,"skater_stats_penalty_minutes":0,"skater_stats_face_off_wins":0,"skater_stats_faceoff_taken":0,"skater_stats_short_handed_goals":0,"skater_stats_short_handed_assists":0,"skater_stats_plus_minus":0,"skater_stats_even_time_on_ice":"13:43","skater_stats_power_play_time_on_ice":"1:28","skater_stats_short_handed_time_on_ice":"0:07","home_away":"Away"},{"id":8468660,"full_name":"Darcy Hordichuk","link":"/api/v1/people/8468660","shoots_catches":"L","roster_status":"N","jersey_number":"24","code":"L","name":"Left Wing","type":"Forward","abbreviation":"LW","skater_stats_time_on_ice":"6:56","skater_stats_assists":0,"skater_stats_goals":0,"skater_stats_shots":0,"skater_stats_power_play_goals":0,"skater_stats_power_play_assists":0,"skater_stats_penalty_minutes":0,"skater_stats_face_off_wins":0,"skater_stats_faceoff_taken":0,"skater_stats_short_handed_goals":0,"skater_stats_short_handed_assists":0,"skater_stats_plus_minus":0,"skater_stats_even_time_on_ice":"6:56","skater_stats_power_play_time_on_ice":"0:00","skater_stats_short_handed_time_on_ice":"0:00","home_away":"Away"},{"id":8471664,"full_name":"Mason Raymond","link":"/api/v1/people/8471664","shoots_catches":"L","roster_status":"N","jersey_number":"21","code":"L","name":"Left Wing","type":"Forward","abbreviation":"LW","skater_stats_time_on_ice":"12:59","skater_stats_assists":0,"skater_stats_goals":0,"skater_stats_shots":1,"skater_stats_power_play_goals":0,"skater_stats_power_play_assists":0,"skater_stats_penalty_minutes":0,"skater_stats_face_off_wins":0,"skater_stats_faceoff_taken":0,"skater_stats_short_handed_goals":0,"skater_stats_short_handed_assists":0,"skater_stats_plus_minus":0,"skater_stats_even_time_on_ice":"9:24","skater_stats_power_play_time_on_ice":"0:05","skater_stats_short_handed_time_on_ice":"3:30","home_away":"Away"},{"id":8466141,"full_name":"Roberto Luongo","link":"/api/v1/people/8466141","shoots_catches":"L","roster_status":"Y","jersey_number":"1","code":"G","name":"Goalie","type":"Goalie","abbreviation":"G","goalie_stats_time_on_ice":"59:56","goalie_stats_assists":0,"goalie_stats_goals":0,"goalie_stats_pim":0,"goalie_stats_shots":27,"goalie_stats_saves":24,"goalie_stats_power_play_saves":3,"goalie_stats_short_handed_saves":1,"goalie_stats_even_saves":20,"goalie_stats_short_handed_shots_against":1,"goalie_stats_even_shots_against":21,"goalie_stats_power_play_shots_against":5,"goalie_stats_decision":"L","goalie_stats_save_percentage":88.8889,"goalie_stats_power_play_save_percentage":60,"goalie_stats_short_handed_save_percentage":100,"goalie_stats_even_strength_save_percentage":95.2381,"home_away":"Away"},{"id":8473488,"full_name":"Sergei Shirokov","link":"/api/v1/people/8473488","shoots_catches":"R","roster_status":"N","jersey_number":"25","code":"L","name":"Left Wing","type":"Forward","abbreviation":"LW","skater_stats_time_on_ice":"15:03","skater_stats_assists":0,"skater_stats_goals":0,"skater_stats_shots":2,"skater_stats_power_play_goals":0,"skater_stats_power_play_assists":0,"skater_stats_penalty_minutes":0,"skater_stats_face_off_wins":0,"skater_stats_faceoff_taken":0,"skater_stats_short_handed_goals":0,"skater_stats_short_handed_assists":0,"skater_stats_plus_minus":0,"skater_stats_even_time_on_ice":"12:55","skater_stats_power_play_time_on_ice":"2:08","skater_stats_short_handed_time_on_ice":"0:00","home_away":"Away"},{"id":8470358,"full_name":"Alexandre Burrows","link":"/api/v1/people/8470358","shoots_catches":"L","roster_status":"Y","jersey_number":"14","code":"L","name":"Left Wing","type":"Forward","abbreviation":"LW","skater_stats_time_on_ice":"17:20","skater_stats_assists":0,"skater_stats_goals":0,"skater_stats_shots":6,"skater_stats_power_play_goals":0,"skater_stats_power_play_assists":0,"skater_stats_penalty_minutes":2,"skater_stats_face_off_wins":1,"skater_stats_faceoff_taken":1,"skater_stats_short_handed_goals":0,"skater_stats_short_handed_assists":0,"skater_stats_plus_minus":-1,"skater_stats_even_time_on_ice":"14:53","skater_stats_power_play_time_on_ice":"0:25","skater_stats_short_handed_time_on_ice":"2:02","skater_stats_face_off_pct":100,"home_away":"Away"},{"id":8471303,"full_name":"Alexander Edler","link":"/api/v1/people/8471303","shoots_catches":"L","roster_status":"Y","jersey_number":"23","code":"D","name":"Defenseman","type":"Defenseman","abbreviation":"D","skater_stats_time_on_ice":"18:55","skater_stats_assists":0,"skater_stats_goals":0,"skater_stats_shots":3,"skater_stats_power_play_goals":0,"skater_stats_power_play_assists":0,"skater_stats_penalty_minutes":2,"skater_stats_face_off_wins":0,"skater_stats_faceoff_taken":0,"skater_stats_short_handed_goals":0,"skater_stats_short_handed_assists":0,"skater_stats_plus_minus":0,"skater_stats_even_time_on_ice":"15:14","skater_stats_power_play_time_on_ice":"2:55","skater_stats_short_handed_time_on_ice":"0:46","home_away":"Away"},{"id":8469581,"full_name":"Kyle Wellwood","link":"/api/v1/people/8469581","shoots_catches":"R","roster_status":"Y","jersey_number":"42","code":"C","name":"Center","type":"Forward","abbreviation":"C","skater_stats_time_on_ice":"12:56","skater_stats_assists":0,"skater_stats_goals":0,"skater_stats_shots":1,"skater_stats_power_play_goals":0,"skater_stats_power_play_assists":0,"skater_stats_penalty_minutes":0,"skater_stats_face_off_wins":2,"skater_stats_faceoff_taken":3,"skater_stats_short_handed_goals":0,"skater_stats_short_handed_assists":0,"skater_stats_plus_minus":-1,"skater_stats_even_time_on_ice":"10:11","skater_stats_power_play_time_on_ice":"2:38","skater_stats_short_handed_time_on_ice":"0:07","skater_stats_face_off_pct":66.67,"home_away":"Away"},{"id":8460527,"full_name":"Ryan Johnson","link":"/api/v1/people/8460527","shoots_catches":"L","roster_status":"N","jersey_number":"10","code":"C","name":"Center","type":"Forward","abbreviation":"C","skater_stats_time_on_ice":"11:05","skater_stats_assists":0,"skater_stats_goals":0,"skater_stats_shots":0,"skater_stats_power_play_goals":0,"skater_stats_power_play_assists":0,"skater_stats_penalty_minutes":0,"skater_stats_face_off_wins":3,"skater_stats_faceoff_taken":10,"skater_stats_short_handed_goals":0,"skater_stats_short_handed_assists":0,"skater_stats_plus_minus":0,"skater_stats_even_time_on_ice":"6:56","skater_stats_power_play_time_on_ice":"0:00","skater_stats_short_handed_time_on_ice":"4:09","skater_stats_face_off_pct":30,"home_away":"Away"},{"id":8469598,"full_name":"Kevin Bieksa","link":"/api/v1/people/8469598","shoots_catches":"R","roster_status":"Y","jersey_number":"3","code":"D","name":"Defenseman","type":"Defenseman","abbreviation":"D","skater_stats_time_on_ice":"22:33","skater_stats_assists":0,"skater_stats_goals":0,"skater_stats_shots":3,"skater_stats_power_play_goals":0,"skater_stats_power_play_assists":0,"skater_stats_penalty_minutes":7,"skater_stats_face_off_wins":0,"skater_stats_faceoff_taken":0,"skater_stats_short_handed_goals":0,"skater_stats_short_handed_assists":0,"skater_stats_plus_minus":0,"skater_stats_even_time_on_ice":"15:28","skater_stats_power_play_time_on_ice":"2:50","skater_stats_short_handed_time_on_ice":"4:15","home_away":"Away"},{"id":8469555,"full_name":"Christian Ehrhoff","link":"/api/v1/people/8469555","shoots_catches":"L","roster_status":"N","jersey_number":"5","code":"D","name":"Defenseman","type":"Defenseman","abbreviation":"D","skater_stats_time_on_ice":"16:18","skater_stats_assists":0,"skater_stats_goals":0,"skater_stats_shots":3,"skater_stats_power_play_goals":0,"skater_stats_power_play_assists":0,"skater_stats_penalty_minutes":0,"skater_stats_face_off_wins":0,"skater_stats_faceoff_taken":0,"skater_stats_short_handed_goals":0,"skater_stats_short_handed_assists":0,"skater_stats_plus_minus":0,"skater_stats_even_time_on_ice":"12:35","skater_stats_power_play_time_on_ice":"2:59","skater_stats_short_handed_time_on_ice":"0:44","home_away":"Away"},{"id":8468611,"full_name":"Matt Hendricks","link":"/api/v1/people/8468611","shoots_catches":"L","roster_status":"Y","jersey_number":"15","code":"L","name":"Left Wing","type":"Forward","abbreviation":"LW","skater_stats_time_on_ice":"10:08","skater_stats_assists":0,"skater_stats_goals":0,"skater_stats_shots":4,"skater_stats_power_play_goals":0,"skater_stats_power_play_assists":0,"skater_stats_penalty_minutes":0,"skater_stats_face_off_wins":1,"skater_stats_faceoff_taken":2,"skater_stats_short_handed_goals":0,"skater_stats_short_handed_assists":0,"skater_stats_plus_minus":0,"skater_stats_even_time_on_ice":"9:14","skater_stats_power_play_time_on_ice":"0:00","skater_stats_short_handed_time_on_ice":"0:54","skater_stats_face_off_pct":50,"home_away":"Home"},{"id":8471669,"full_name":"Paul Stastny","link":"/api/v1/people/8471669","shoots_catches":"L","roster_status":"Y","jersey_number":"26","code":"C","name":"Center","type":"Forward","abbreviation":"C","skater_stats_time_on_ice":"18:47","skater_stats_assists":1,"skater_stats_goals":1,"skater_stats_shots":1,"skater_stats_power_play_goals":1,"skater_stats_power_play_assists":0,"skater_stats_penalty_minutes":2,"skater_stats_face_off_wins":8,"skater_stats_faceoff_taken":17,"skater_stats_short_handed_goals":0,"skater_stats_short_handed_assists":0,"skater_stats_plus_minus":1,"skater_stats_even_time_on_ice":"12:24","skater_stats_power_play_time_on_ice":"5:18","skater_stats_short_handed_time_on_ice":"1:05","skater_stats_face_off_pct":47.06,"home_away":"Home"},{"id":8471879,"full_name":"Kyle Cumiskey","link":"/api/v1/people/8471879","shoots_catches":"L","roster_status":"N","jersey_number":"10","code":"D","name":"Defenseman","type":"Defenseman","abbreviation":"D","skater_stats_time_on_ice":"16:13","skater_stats_assists":0,"skater_stats_goals":0,"skater_stats_shots":0,"skater_stats_power_play_goals":0,"skater_stats_power_play_assists":0,"skater_stats_penalty_minutes":0,"skater_stats_face_off_wins":0,"skater_stats_faceoff_taken":0,"skater_stats_short_handed_goals":0,"skater_stats_short_handed_assists":0,"skater_stats_plus_minus":1,"skater_stats_even_time_on_ice":"11:37","skater_stats_power_play_time_on_ice":"3:27","skater_stats_short_handed_time_on_ice":"1:09","home_away":"Home"},{"id":8466158,"full_name":"Scott Hannan","link":"/api/v1/people/8466158","shoots_catches":"L","roster_status":"Y","jersey_number":"22","code":"D","name":"Defenseman","type":"Defenseman","abbreviation":"D","skater_stats_time_on_ice":"18:36","skater_stats_assists":0,"skater_stats_goals":0,"skater_stats_shots":0,"skater_stats_power_play_goals":0,"skater_stats_power_play_assists":0,"skater_stats_penalty_minutes":0,"skater_stats_face_off_wins":0,"skater_stats_faceoff_taken":0,"skater_stats_short_handed_goals":0,"skater_stats_short_handed_assists":0,"skater_stats_plus_minus":0,"skater_stats_even_time_on_ice":"15:01","skater_stats_power_play_time_on_ice":"0:02","skater_stats_short_handed_time_on_ice":"3:33","home_away":"Home"},{"id":8470724,"full_name":"Kyle Quincey","link":"/api/v1/people/8470724","shoots_catches":"L","roster_status":"Y","jersey_number":"27","code":"D","name":"Defenseman","type":"Defenseman","abbreviation":"D","skater_stats_time_on_ice":"23:35","skater_stats_assists":1,"skater_stats_goals":0,"skater_stats_shots":0,"skater_stats_power_play_goals":0,"skater_stats_power_play_assists":1,"skater_stats_penalty_minutes":2,"skater_stats_face_off_wins":0,"skater_stats_faceoff_taken":0,"skater_stats_short_handed_goals":0,"skater_stats_short_handed_assists":0,"skater_stats_plus_minus":0,"skater_stats_even_time_on_ice":"15:23","skater_stats_power_play_time_on_ice":"5:49","skater_stats_short_handed_time_on_ice":"2:23","home_away":"Home"},{"id":8467950,"full_name":"Craig Anderson","link":"/api/v1/people/8467950","shoots_catches":"L","roster_status":"Y","jersey_number":"41","code":"G","name":"Goalie","type":"Goalie","abbreviation":"G","goalie_stats_time_on_ice":"59:44","goalie_stats_assists":0,"goalie_stats_goals":0,"goalie_stats_pim":0,"goalie_stats_shots":35,"goalie_stats_saves":35,"goalie_stats_power_play_saves":7,"goalie_stats_short_handed_saves":1,"goalie_stats_even_saves":27,"goalie_stats_short_handed_shots_against":1,"goalie_stats_even_shots_against":27,"goalie_stats_power_play_shots_against":7,"goalie_stats_decision":"W","goalie_stats_save_percentage":100,"goalie_stats_power_play_save_percentage":100,"goalie_stats_short_handed_save_percentage":100,"goalie_stats_even_strength_save_percentage":100,"home_away":"Home"},{"id":8465122,"full_name":"Brett Clark","link":"/api/v1/people/8465122","shoots_catches":"L","roster_status":"N","jersey_number":"5","code":"D","name":"Defenseman","type":"Defenseman","abbreviation":"D","skater_stats_time_on_ice":"20:09","skater_stats_assists":1,"skater_stats_goals":0,"skater_stats_shots":1,"skater_stats_power_play_goals":0,"skater_stats_power_play_assists":1,"skater_stats_penalty_minutes":0,"skater_stats_face_off_wins":0,"skater_stats_faceoff_taken":0,"skater_stats_short_handed_goals":0,"skater_stats_short_handed_assists":0,"skater_stats_plus_minus":1,"skater_stats_even_time_on_ice":"13:06","skater_stats_power_play_time_on_ice":"4:26","skater_stats_short_handed_time_on_ice":"2:37","home_away":"Home"},{"id":8459574,"full_name":"Darcy Tucker","link":"/api/v1/people/8459574","shoots_catches":"L","roster_status":"Y","jersey_number":"16","code":"R","name":"Right Wing","type":"Forward","abbreviation":"RW","skater_stats_time_on_ice":"15:27","skater_stats_assists":0,"skater_stats_goals":1,"skater_stats_shots":5,"skater_stats_power_play_goals":1,"skater_stats_power_play_assists":0,"skater_stats_penalty_minutes":7,"skater_stats_face_off_wins":2,"skater_stats_faceoff_taken":2,"skater_stats_short_handed_goals":0,"skater_stats_short_handed_assists":0,"skater_stats_plus_minus":0,"skater_stats_even_time_on_ice":"11:29","skater_stats_power_play_time_on_ice":"3:56","skater_stats_short_handed_time_on_ice":"0:02","skater_stats_face_off_pct":100,"home_away":"Home"},{"id":8456283,"full_name":"Adam Foote","link":"/api/v1/people/8456283","shoots_catches":"R","roster_status":"Y","jersey_number":"52","code":"D","name":"Defenseman","type":"Defenseman","abbreviation":"D","skater_stats_time_on_ice":"20:10","skater_stats_assists":0,"skater_stats_goals":0,"skater_stats_shots":1,"skater_stats_power_play_goals":0,"skater_stats_power_play_assists":0,"skater_stats_penalty_minutes":2,"skater_stats_face_off_wins":0,"skater_stats_faceoff_taken":0,"skater_stats_short_handed_goals":0,"skater_stats_short_handed_assists":0,"skater_stats_plus_minus":0,"skater_stats_even_time_on_ice":"18:40","skater_stats_power_play_time_on_ice":"0:00","skater_stats_short_handed_time_on_ice":"1:30","home_away":"Home"},{"id":8471234,"full_name":"Wojtek Wolski","link":"/api/v1/people/8471234","shoots_catches":"L","roster_status":"Y","jersey_number":"8","code":"L","name":"Left Wing","type":"Forward","abbreviation":"LW","skater_stats_time_on_ice":"15:16","skater_stats_assists":1,"skater_stats_goals":1,"skater_stats_shots":6,"skater_stats_power_play_goals":0,"skater_stats_power_play_assists":1,"skater_stats_penalty_minutes":0,"skater_stats_face_off_wins":1,"skater_stats_faceoff_taken":2,"skater_stats_short_handed_goals":0,"skater_stats_short_handed_assists":0,"skater_stats_plus_minus":1,"skater_stats_even_time_on_ice":"11:44","skater_stats_power_play_time_on_ice":"3:32","skater_stats_short_handed_time_on_ice":"0:00","skater_stats_face_off_pct":50,"home_away":"Home"},{"id":8471657,"full_name":"Cody McLeod","link":"/api/v1/people/8471657","shoots_catches":"L","roster_status":"Y","jersey_number":"55","code":"L","name":"Left Wing","type":"Forward","abbreviation":"LW","skater_stats_time_on_ice":"15:15","skater_stats_assists":0,"skater_stats_goals":0,"skater_stats_shots":2,"skater_stats_power_play_goals":0,"skater_stats_power_play_assists":0,"skater_stats_penalty_minutes":5,"skater_stats_face_off_wins":1,"skater_stats_faceoff_taken":1,"skater_stats_short_handed_goals":0,"skater_stats_short_handed_assists":0,"skater_stats_plus_minus":0,"skater_stats_even_time_on_ice":"13:41","skater_stats_power_play_time_on_ice":"0:04","skater_stats_short_handed_time_on_ice":"1:30","skater_stats_face_off_pct":100,"home_away":"Home"},{"id":8475168,"full_name":"Matt Duchene","link":"/api/v1/people/8475168","shoots_catches":"L","roster_status":"Y","jersey_number":"9","code":"C","name":"Center","type":"Forward","abbreviation":"C","skater_stats_time_on_ice":"15:29","skater_stats_assists":0,"skater_stats_goals":0,"skater_stats_shots":2,"skater_stats_power_play_goals":0,"skater_stats_power_play_assists":0,"skater_stats_penalty_minutes":0,"skater_stats_face_off_wins":4,"skater_stats_faceoff_taken":11,"skater_stats_short_handed_goals":0,"skater_stats_short_handed_assists":0,"skater_stats_plus_minus":0,"skater_stats_even_time_on_ice":"8:53","skater_stats_power_play_time_on_ice":"5:31","skater_stats_short_handed_time_on_ice":"1:05","skater_stats_face_off_pct":36.36,"home_away":"Home"},{"id":8475158,"full_name":"Ryan O'Reilly","link":"/api/v1/people/8475158","shoots_catches":"L","roster_status":"Y","jersey_number":"37","code":"C","name":"Center","type":"Forward","abbreviation":"C","skater_stats_time_on_ice":"13:03","skater_stats_assists":0,"skater_stats_goals":0,"skater_stats_shots":1,"skater_stats_power_play_goals":0,"skater_stats_power_play_assists":0,"skater_stats_penalty_minutes":0,"skater_stats_face_off_wins":4,"skater_stats_faceoff_taken":6,"skater_stats_short_handed_goals":0,"skater_stats_short_handed_assists":0,"skater_stats_plus_minus":0,"skater_stats_even_time_on_ice":"10:12","skater_stats_power_play_time_on_ice":"0:02","skater_stats_short_handed_time_on_ice":"2:49","skater_stats_face_off_pct":66.67,"home_away":"Home"},{"id":8473485,"full_name":"Chris Stewart","link":"/api/v1/people/8473485","shoots_catches":"R","roster_status":"Y","jersey_number":"25","code":"R","name":"Right Wing","type":"Forward","abbreviation":"RW","skater_stats_time_on_ice":"17:24","skater_stats_assists":0,"skater_stats_goals":0,"skater_stats_shots":0,"skater_stats_power_play_goals":0,"skater_stats_power_play_assists":0,"skater_stats_penalty_minutes":0,"skater_stats_face_off_wins":0,"skater_stats_faceoff_taken":0,"skater_stats_short_handed_goals":0,"skater_stats_short_handed_assists":0,"skater_stats_plus_minus":0,"skater_stats_even_time_on_ice":"17:05","skater_stats_power_play_time_on_ice":"0:17","skater_stats_short_handed_time_on_ice":"0:02","home_away":"Home"},{"id":8469670,"full_name":"Marek Svatos","link":"/api/v1/people/8469670","shoots_catches":"R","roster_status":"N","jersey_number":"40","code":"R","name":"Right Wing","type":"Forward","abbreviation":"RW","skater_stats_time_on_ice":"11:54","skater_stats_assists":0,"skater_stats_goals":0,"skater_stats_shots":1,"skater_stats_power_play_goals":0,"skater_stats_power_play_assists":0,"skater_stats_penalty_minutes":0,"skater_stats_face_off_wins":0,"skater_stats_faceoff_taken":0,"skater_stats_short_handed_goals":0,"skater_stats_short_handed_assists":0,"skater_stats_plus_minus":0,"skater_stats_even_time_on_ice":"7:47","skater_stats_power_play_time_on_ice":"4:07","skater_stats_short_handed_time_on_ice":"0:00","home_away":"Home"},{"id":8474001,"full_name":"TJ Galiardi","link":"/api/v1/people/8474001","shoots_catches":"L","roster_status":"N","jersey_number":"39","code":"L","name":"Left Wing","type":"Forward","abbreviation":"LW","skater_stats_time_on_ice":"16:54","skater_stats_assists":0,"skater_stats_goals":0,"skater_stats_shots":1,"skater_stats_power_play_goals":0,"skater_stats_power_play_assists":0,"skater_stats_penalty_minutes":0,"skater_stats_face_off_wins":2,"skater_stats_faceoff_taken":10,"skater_stats_short_handed_goals":0,"skater_stats_short_handed_assists":0,"skater_stats_plus_minus":0,"skater_stats_even_time_on_ice":"13:16","skater_stats_power_play_time_on_ice":"0:44","skater_stats_short_handed_time_on_ice":"2:54","skater_stats_face_off_pct":20,"home_away":"Home"},{"id":8460577,"full_name":"Milan Hejduk","link":"/api/v1/people/8460577","shoots_catches":"R","roster_status":"Y","jersey_number":"23","code":"R","name":"Right Wing","type":"Forward","abbreviation":"RW","skater_stats_time_on_ice":"20:53","skater_stats_assists":2,"skater_stats_goals":0,"skater_stats_shots":1,"skater_stats_power_play_goals":0,"skater_stats_power_play_assists":1,"skater_stats_penalty_minutes":0,"skater_stats_face_off_wins":0,"skater_stats_faceoff_taken":0,"skater_stats_short_handed_goals":0,"skater_stats_short_handed_assists":0,"skater_stats_plus_minus":1,"skater_stats_even_time_on_ice":"14:32","skater_stats_power_play_time_on_ice":"5:02","skater_stats_short_handed_time_on_ice":"1:19","home_away":"Home"},{"id":8468639,"full_name":"John-Michael Liles","link":"/api/v1/people/8468639","shoots_catches":"L","roster_status":"Y","jersey_number":"4","code":"D","name":"Defenseman","type":"Defenseman","abbreviation":"D","skater_stats_time_on_ice":"21:53","skater_stats_assists":0,"skater_stats_goals":0,"skater_stats_shots":1,"skater_stats_power_play_goals":0,"skater_stats_power_play_assists":0,"skater_stats_penalty_minutes":0,"skater_stats_face_off_wins":0,"skater_stats_faceoff_taken":0,"skater_stats_short_handed_goals":0,"skater_stats_short_handed_assists":0,"skater_stats_plus_minus":0,"skater_stats_even_time_on_ice":"16:07","skater_stats_power_play_time_on_ice":"5:18","skater_stats_short_handed_time_on_ice":"0:28","home_away":"Home"},{"id":8468626,"full_name":"David Koci","link":"/api/v1/people/8468626","shoots_catches":"L","roster_status":"Y","jersey_number":"28","code":"L","name":"Left Wing","type":"Forward","abbreviation":"LW","skater_stats_time_on_ice":"1:20","skater_stats_assists":0,"skater_stats_goals":0,"skater_stats_shots":0,"skater_stats_power_play_goals":0,"skater_stats_power_play_assists":0,"skater_stats_penalty_minutes":0,"skater_stats_face_off_wins":0,"skater_stats_faceoff_taken":0,"skater_stats_short_handed_goals":0,"skater_stats_short_handed_assists":0,"skater_stats_plus_minus":0,"skater_stats_even_time_on_ice":"1:20","skater_stats_power_play_time_on_ice":"0:00","skater_stats_short_handed_time_on_ice":"0:00","home_away":"Home"}],"skaters":[{"skaters":8469598,"home_away":"Away"},{"skaters":8469555,"home_away":"Away"},{"skaters":8465202,"home_away":"Away"},{"skaters":8465185,"home_away":"Away"},{"skaters":8460527,"home_away":"Away"},{"skaters":8470358,"home_away":"Away"},{"skaters":8470616,"home_away":"Away"},{"skaters":8470609,"home_away":"Away"},{"skaters":8471664,"home_away":"Away"},{"skaters":8467875,"home_away":"Away"},{"skaters":8471303,"home_away":"Away"},{"skaters":8468660,"home_away":"Away"},{"skaters":8473488,"home_away":"Away"},{"skaters":8467463,"home_away":"Away"},{"skaters":8467876,"home_away":"Away"},{"skaters":8471628,"home_away":"Away"},{"skaters":8469581,"home_away":"Away"},{"skaters":8470839,"home_away":"Away"},{"skaters":8470310,"home_away":"Away"},{"skaters":8470854,"home_away":"Away"},{"skaters":8468639,"home_away":"Home"},{"skaters":8465122,"home_away":"Home"},{"skaters":8471234,"home_away":"Home"},{"skaters":8475168,"home_away":"Home"},{"skaters":8471879,"home_away":"Home"},{"skaters":8468611,"home_away":"Home"},{"skaters":8459574,"home_away":"Home"},{"skaters":8466158,"home_away":"Home"},{"skaters":8460577,"home_away":"Home"},{"skaters":8473485,"home_away":"Home"},{"skaters":8471669,"home_away":"Home"},{"skaters":8470724,"home_away":"Home"},{"skaters":8468626,"home_away":"Home"},{"skaters":8475158,"home_away":"Home"},{"skaters":8474001,"home_away":"Home"},{"skaters":8469670,"home_away":"Home"},{"skaters":8456283,"home_away":"Home"},{"skaters":8471657,"home_away":"Home"},{"skaters":8464962,"home_away":"Home"},{"skaters":8470877,"home_away":"Home"},{"skaters":8471753,"home_away":"Home"}],"goalies":[{"goalies":8466141,"home_away":"Away"},{"goalies":8467950,"home_away":"Home"}],"on_ice":[],"on_ice_plus":[],"penalty_box":[],"scratches":[{"scratches":8470310},{"scratches":8470854},{"scratches":8464962},{"scratches":8470877},{"scratches":8471753}],"team_coaches":[{"person.fullName":"Alain Vigneault","person.link":"/api/v1/people/null","position.code":"HC","position.name":"Head Coach","position.type":"Head Coach","position.abbreviation":"Head Coach","home_away":"Away"},{"person.fullName":"Joe Sacco","person.link":"/api/v1/people/null","position.code":"HC","position.name":"Head Coach","position.type":"Head Coach","position.abbreviation":"Head Coach","home_away":"Home"}]}
